{
        "iconSize": 16,
        "durability": 256,
        "equipType": 3,
        "numOfStyles": 1,
        "rarity": 5,

        "sounds": [
                ["actions/hit"]
        ],
        
        "bonusMagic": 3,
        "minDamage": 85,
        "maxDamage": 95 ,
        "hitRange": 7,
        "manaCost": 20,
        
        "elementDamage":"earth",
        "projectile": "earth-ball",
        "shootType":  12,
        "weaponType": "wand",
        "weight": "2300",
        "description": "",
        
        "level": 200,
        "vocations": [
                {"name":"2"}
	]
}